InternetArchiveUploader/InternetArchiveUploader.py
InternetArchiveUploader/__init__.py
internet_archive_uploader-1.2.7.dist-info/LICENSE
internet_archive_uploader-1.2.7.dist-info/METADATA
internet_archive_uploader-1.2.7.dist-info/WHEEL
internet_archive_uploader-1.2.7.dist-info/top_level.txt
internet_archive_uploader-1.2.7.dist-info/RECORD
