Metadata-Version: 2.1
Name: internet-archive-uploader
Version: 1.2.7
Summary: A wrapper around the internetarchive package for uploading files and directorys
Home-page: https://github.com/jgore077/Internet-Archive-Uploader/blob/master/README.md
Author: James Gore
Author-email: jgore077@gmail.com
License: MIT
Requires-Python: >=3.6,<=3.13
License-File: LICENSE
Requires-Dist: internetarchive >=3.6.0
